{"class": "org.mayukh.footprint.model.auto.GpsUnit", "fields": [{"variable": "make","type": "java.lang.String","value": "Pom Pom"},{"variable": "provider","type": "java.lang.String","value": "Google"},{"variable": "battery","type": "org.mayukh.footprint.model.auto.Battery","ref": {"class": "org.mayukh.footprint.model.auto.Battery", "fields": [{"variable": "name","type": "java.lang.String","value": "Lithium-Ion"},{"variable": "manufactured","type": "java.time.LocalDate","value": "2016-08-20"},{"variable": "chargeLeft","type": "java.lang.Double","value": "20.0"}]}}]}
